marsimage/__init__.py
marsimage/__version__.py
marsimage/batch_processing.py
marsimage/const.py
marsimage/dng.py
marsimage/download.py
marsimage/filename.py
marsimage/image.py
marsimage/imagebase.py
marsimage/imgutils.py
marsimage/instrument_defs.py
marsimage/metautils.py
marsimage/save.py
marsimage/data/instrument_defs.toml
marsimage/frames/__init__.py
marsimage/frames/camera_model.py
marsimage/frames/coordinate_frames.py
marsimage/frames/localization.py
marsimage/lib/README.md
marsimage/lib/__init__.py
marsimage/lib/exiftool.py
marsimage/lib/rawtherapee.py
marsimage/lib/exiftool/unix/.ExifTool_config
marsimage/lib/exiftool/unix/exiftool
marsimage/lib/exiftool/unix/lib/File/RandomAccess.pm
marsimage/lib/exiftool/unix/lib/File/RandomAccess.pod
marsimage/lib/exiftool/unix/lib/Image/ExifTool.pm
marsimage/lib/exiftool/unix/lib/Image/ExifTool.pod
marsimage/lib/exiftool/unix/lib/Image/ExifTool/7Z.pm
marsimage/lib/exiftool/unix/lib/Image/ExifTool/AAC.pm
marsimage/lib/exiftool/unix/lib/Image/ExifTool/AES.pm
marsimage/lib/exiftool/unix/lib/Image/ExifTool/AFCP.pm
marsimage/lib/exiftool/unix/lib/Image/ExifTool/AIFF.pm
marsimage/lib/exiftool/unix/lib/Image/ExifTool/APE.pm
marsimage/lib/exiftool/unix/lib/Image/ExifTool/APP12.pm
marsimage/lib/exiftool/unix/lib/Image/ExifTool/ASF.pm
marsimage/lib/exiftool/unix/lib/Image/ExifTool/Apple.pm
marsimage/lib/exiftool/unix/lib/Image/ExifTool/Audible.pm
marsimage/lib/exiftool/unix/lib/Image/ExifTool/BMP.pm
marsimage/lib/exiftool/unix/lib/Image/ExifTool/BPG.pm
marsimage/lib/exiftool/unix/lib/Image/ExifTool/BZZ.pm
marsimage/lib/exiftool/unix/lib/Image/ExifTool/BigTIFF.pm
marsimage/lib/exiftool/unix/lib/Image/ExifTool/BuildTagLookup.pm
marsimage/lib/exiftool/unix/lib/Image/ExifTool/CBOR.pm
marsimage/lib/exiftool/unix/lib/Image/ExifTool/Canon.pm
marsimage/lib/exiftool/unix/lib/Image/ExifTool/CanonCustom.pm
marsimage/lib/exiftool/unix/lib/Image/ExifTool/CanonRaw.pm
marsimage/lib/exiftool/unix/lib/Image/ExifTool/CanonVRD.pm
marsimage-0.1.2.dist-info/METADATA
marsimage-0.1.2.dist-info/WHEEL
marsimage-0.1.2.dist-info/licenses/LICENSE.txt
marsimage-0.1.2.dist-info/RECORD
