Metadata-Version: 2.4
Name: marsimage
Version: 0.1.2
Summary: Python package for processing and analyzing images from the NASA Mars rovers.
Project-URL: Source, https://gitlab.univ-nantes.fr/mars-rovers/marsimage/
Project-URL: Documentation, https://marsimage.readthedocs.io/
Author-email: Simeon Schmauß <simeon.schmauss@gmail.com>, Benoît Seignovert <benoit.seignovert@univ-nantes.fr>
Maintainer-email: Simeon Schmauß <simeon.schmauss@gmail.com>, Benoît Seignovert <benoit.seignovert@univ-nantes.fr>
License-Expression: MIT
License-File: LICENSE.txt
Keywords: image,mars,nasa,pds
Classifier: Development Status :: 4 - Beta
Classifier: Programming Language :: Python
Classifier: Programming Language :: Python :: 3.11
Classifier: Programming Language :: Python :: 3.12
Requires-Python: >=3.11
Requires-Dist: matplotlib
Requires-Dist: numpy
Requires-Dist: pandas
Requires-Dist: pdr
Requires-Dist: requests
Requires-Dist: scipy
Requires-Dist: tifffile
Requires-Dist: tqdm
Provides-Extra: jupyter
Requires-Dist: ipykernel; extra == 'jupyter'
Requires-Dist: ipywidgets; extra == 'jupyter'
